{
  "appName": "app1",
  "appVersion": "1.0.2",
  "deploymentId": "4d828a97-0ed7-467f-bf18-ca4a9576369c",
  "generationTimestamp": "2025-06-04T06:14:43.840584",
  "generator": "Python IaC Script",
  "uniqueId": "app1-4d828a97-0ed7-467f-bf18-ca4a9576369c",
  "parametersReceived": {
    "app_name": "app1",
    "app_port": "8081",
    "deployment_id": "4d828a97-0ed7-467f-bf18-ca4a9576369c",
    "input_data": "datos_adicionales_para_python",
    "q1": "v1",
    "q10": "v10",
    "q11": "v11",
    "q12": "v12",
    "q13": "v13",
    "q14": "v14",
    "q15": "v15",
    "q16": "v16",
    "q17": "v17",
    "q18": "v18",
    "q19": "v19",
    "q2": "v2",
    "q20": "v20",
    "q3": "v3",
    "q4": "v4",
    "q5": "v5",
    "q6": "v6",
    "q7": "v7",
    "q8": "v8",
    "q9": "v9",
    "version": "1.0.2"
  },
  "simulatedComplexity": {
    "generated_data_points": [
      "Simulated data point 0 for app1 v1.0.2 - 72269c22-dee5-41d7-97cd-dcb958dbb1df",
      "Simulated data point 1 for app1 v1.0.2 - 2f523c65-9c6a-4332-ba65-570c913dbab7",
      "Simulated data point 2 for app1 v1.0.2 - 31c821b2-1f94-4c76-9ee6-9e2c2623aaa2",
      "Simulated data point 3 for app1 v1.0.2 - b183ba54-36dc-4a03-ad15-7f67ee877d8c",
      "Simulated data point 4 for app1 v1.0.2 - b92892f4-8ca0-4975-8c1a-e96816acf82a",
      "Simulated data point 5 for app1 v1.0.2 - 3a829970-3afe-4717-be3f-8df4707288bc",
      "Simulated data point 6 for app1 v1.0.2 - cf358df0-083b-4be1-a8bf-b38b7ad92fef",
      "Simulated data point 7 for app1 v1.0.2 - 0dd0eea7-5e0a-404a-9eec-7b65be2992b2",
      "Simulated data point 8 for app1 v1.0.2 - 406dc7a8-6b41-454c-9ec6-3922b3eefe24",
      "Simulated data point 9 for app1 v1.0.2 - bd28f9a1-d017-4c48-8a9f-de0a0f318808",
      "Simulated data point 10 for app1 v1.0.2 - d6835a5b-70f5-449b-bcaf-fc7c93f83a15",
      "Simulated data point 11 for app1 v1.0.2 - dbd791f7-84db-4979-a8cf-bce1e84a7c3f",
      "Simulated data point 12 for app1 v1.0.2 - f1ed59df-c3bb-4e2d-835d-cdf3efc80caa",
      "Simulated data point 13 for app1 v1.0.2 - e6303a93-4d35-4513-8a7b-d8e32dd4bf34",
      "Simulated data point 14 for app1 v1.0.2 - de3c54de-6e07-4636-9469-7c291d459517"
    ],
    "simulated_dependencies": {
      "dep_0": "version_0.1",
      "dep_1": "version_1.2",
      "dep_2": "version_2.3",
      "dep_3": "version_3.4",
      "dep_4": "version_4.5",
      "dep_5": "version_5.6",
      "dep_6": "version_6.7",
      "dep_7": "version_7.8",
      "dep_8": "version_8.9",
      "dep_9": "version_9.10"
    },
    "calculated_metrics": {
      "val_0": 0.0,
      "val_1": 66.66666666666667,
      "val_2": 80.0,
      "val_3": 85.71428571428571,
      "val_4": 88.88888888888889,
      "val_5": 90.9090909090909,
      "val_6": 92.3076923076923,
      "val_7": 93.33333333333333,
      "val_8": 94.11764705882354,
      "val_9": 94.73684210526316
    },
    "generation_details": [
      "Detail line 0",
      "Detail line 1",
      "Detail line 2",
      "Detail line 3",
      "Detail line 4",
      "Detail line 5",
      "Detail line 6",
      "Detail line 7",
      "Detail line 8",
      "Detail line 9",
      "Detail line 10",
      "Detail line 11",
      "Detail line 12",
      "Detail line 13",
      "Detail line 14"
    ]
  },
  "additional_info": [
    "Linea info 0",
    "Linea info 1",
    "Linea info 2",
    "Linea info 3",
    "Linea info 4",
    "Linea info 5",
    "Linea info 6",
    "Linea info 7",
    "Linea info 8",
    "Linea info 9"
  ],
  "status_flags": {
    "flag_0": true,
    "flag_1": false,
    "flag_2": true,
    "flag_3": false,
    "flag_4": true,
    "flag_5": false,
    "flag_6": true,
    "flag_7": false,
    "flag_8": true,
    "flag_9": false
  },
  "processing_log": [
    "Entrada log 0: Item procesado 9d9949c7-7d9f-40ad-9d98-76664059d0d0",
    "Entrada log 1: Item procesado 1d5f2cab-990b-4dfe-a36f-90549e775a15",
    "Entrada log 2: Item procesado 7cd07d5e-86ba-4655-a668-b4ed01bf9450",
    "Entrada log 3: Item procesado 24048934-851a-4f80-aad5-939001d25c6d",
    "Entrada log 4: Item procesado a1680625-96ea-4f5c-8ebd-6f6b2dc84542",
    "Entrada log 5: Item procesado d91004e3-a33e-4082-98b5-8b87d314144a",
    "Entrada log 6: Item procesado 620ea16c-20ec-4047-a009-48e1ec0cb977",
    "Entrada log 7: Item procesado 566a397e-7c1a-4beb-885f-0f6732cde874",
    "Entrada log 8: Item procesado 77698645-75c7-4a41-8036-9e7d2abfac53",
    "Entrada log 9: Item procesado f847157b-67ea-470c-b944-a3889368cf46",
    "Entrada log 10: Item procesado e899edf0-eca7-4211-9ea9-ffdec47e4000",
    "Entrada log 11: Item procesado b8ef17a4-ecb5-49de-85ca-a64ba127f55d",
    "Entrada log 12: Item procesado 35e5ab11-84e1-4514-a9aa-827efc6f9308",
    "Entrada log 13: Item procesado 3a6c50b0-fcf0-457b-ab0a-521f9e415444",
    "Entrada log 14: Item procesado 4bf245f5-1279-4ff1-b32b-7c661c7ccd31",
    "Entrada log 15: Item procesado 62aa4b6d-9f5e-4a9b-aa9c-e64d77259607",
    "Entrada log 16: Item procesado b8164d5c-9158-4971-b9a0-2654de819031",
    "Entrada log 17: Item procesado 81b27276-251a-4fe2-99e2-b0e3b042416e",
    "Entrada log 18: Item procesado c55ec2fc-3911-4194-8ada-0b777795a668",
    "Entrada log 19: Item procesado bd3f0ebd-d993-4f72-acf2-fe531023c7c0",
    "Entrada log 20: Item procesado e56a1c49-e85d-41b7-b310-daa2aedd6a05",
    "Entrada log 21: Item procesado 0bb15843-657e-4e80-b9bd-0ef0d9aa2eb3",
    "Entrada log 22: Item procesado 550e3bb5-e47c-4fe5-9ae6-ffb25c002305",
    "Entrada log 23: Item procesado cae6e957-6674-4a58-9e10-f50f07eda0a6",
    "Entrada log 24: Item procesado 9483285b-b4e2-4c7e-8d37-2de32b358295",
    "Entrada log 25: Item procesado a957a9f8-dc11-4a16-a439-4851d5beb136",
    "Entrada log 26: Item procesado f7656c16-a01f-4837-a30b-c280b71e4ab1",
    "Entrada log 27: Item procesado 10895d38-af54-4557-ae54-7631ca636a2c",
    "Entrada log 28: Item procesado d9506d02-d3d8-4b16-a218-58b3f52b53a6",
    "Entrada log 29: Item procesado 7f93eab5-59a7-4828-8915-a762b2e218ea"
  ]
}